diffeqzoo/__init__.py
diffeqzoo/_version.py
diffeqzoo/bvps.py
diffeqzoo/transform.py
diffeqzoo/vector_fields.py
diffeqzoo/ivps/__init__.py
diffeqzoo/ivps/_chaos.py
diffeqzoo/ivps/_epidem.py
diffeqzoo/ivps/_ivp.py
diffeqzoo/ivps/_misc.py
diffeqzoo/ivps/_nbody.py
diffeqzoo/ivps/_oscillators.py
diffeqzoo/ivps/_pde.py
diffeqzoo/ivps/_reactions.py
tests/__init__.py
tests/test_bvps.py
tests/test_ivps.py
diffeqzoo-0.0.5.dist-info/LICENSE
diffeqzoo-0.0.5.dist-info/METADATA
diffeqzoo-0.0.5.dist-info/WHEEL
diffeqzoo-0.0.5.dist-info/top_level.txt
diffeqzoo-0.0.5.dist-info/RECORD
