Metadata-Version: 2.1
Name: diffeqzoo
Version: 0.0.5
Summary: Ordinary differential equation zoo
Author: Nicholas Krämer
Author-email: nicholas.kraemer@uni-tuebingen.de
License: MIT
Requires-Python: >=3.8
License-File: LICENSE
Provides-Extra: example
Requires-Dist: jupyter ; extra == 'example'
Requires-Dist: matplotlib ; extra == 'example'
Requires-Dist: scipy ; extra == 'example'
Requires-Dist: jupytext ; extra == 'example'
Requires-Dist: diffrax ; extra == 'example'
Provides-Extra: jax
Requires-Dist: jax[cpu] ; extra == 'jax'
Provides-Extra: lint
Requires-Dist: flake8 ; extra == 'lint'
Requires-Dist: flake8-docstrings ; extra == 'lint'
Requires-Dist: isort ; extra == 'lint'
Requires-Dist: black ; extra == 'lint'
Requires-Dist: nbqa ; extra == 'lint'
Requires-Dist: jupytext ; extra == 'lint'
Requires-Dist: pylint ; extra == 'lint'
Provides-Extra: numpy
Requires-Dist: numpy ; extra == 'numpy'
Provides-Extra: test
Requires-Dist: pytest ; extra == 'test'
Requires-Dist: pytest-randomly ; extra == 'test'
Requires-Dist: pytest-cases ; extra == 'test'
Requires-Dist: jax[cpu] ; extra == 'test'
Requires-Dist: numpy ; extra == 'test'
